homomer_count/__init__.py
homomer_count/main.py
homomer_count-1.0.6.data/scripts/homomer_count
homomer_count-1.0.6.dist-info/LICENSE
homomer_count-1.0.6.dist-info/METADATA
homomer_count-1.0.6.dist-info/WHEEL
homomer_count-1.0.6.dist-info/top_level.txt
homomer_count-1.0.6.dist-info/RECORD
